hiplt/__init__.py
hiplt/acs.py
hiplt/bridge.py
hiplt/cmd.py
hiplt/config.py
hiplt/core.py
hiplt/db.py
hiplt/gui.py
hiplt/locale.py
hiplt/net.py
hiplt/plugins.py
hiplt/router.py
hiplt/scheduler.py
hiplt/shell.py
hiplt/system.py
hiplt/telemetry.py
hiplt/types.py
hiplt/utils.py
hiplt-0.2.3.dist-info/licenses/LICENSE.md
hiplt-0.2.3.dist-info/METADATA
hiplt-0.2.3.dist-info/WHEEL
hiplt-0.2.3.dist-info/top_level.txt
hiplt-0.2.3.dist-info/RECORD
