Metadata-Version: 2.4
Name: hiplt
Version: 0.2.3
Summary: hiplt — компонентная плагин-система, команды, API и конфиги в одном.
Home-page: https://github.com/CSOforyou/hip
Author: CSOforyou
Author-email: defolt032@gmail.com
Project-URL: Bug Tracker, https://github.com/CSOforyou/hip/issues
Project-URL: Source, https://github.com/CSOforyou/hip
Keywords: hip plugins modular cli api configuration framework
Classifier: Programming Language :: Python :: 3
Classifier: Programming Language :: Python :: 3.8
Classifier: Programming Language :: Python :: 3.9
Classifier: Programming Language :: Python :: 3.10
Classifier: Operating System :: OS Independent
Classifier: License :: OSI Approved :: MIT License
Classifier: Development Status :: 4 - Beta
Classifier: Intended Audience :: Developers
Classifier: Topic :: Software Development :: Libraries :: Application Frameworks
Requires-Python: >=3.8
License-File: LICENSE.md
Requires-Dist: requests
Dynamic: author
Dynamic: author-email
Dynamic: classifier
Dynamic: description
Dynamic: description-content-type
Dynamic: home-page
Dynamic: keywords
Dynamic: license-file
Dynamic: project-url
Dynamic: requires-dist
Dynamic: requires-python
Dynamic: summary
